{
  "parent": "minecraft:recipes/root",
  "rewards": {
    "recipes": [
      "electromatic:light_blue_copper_wire"
    ]
  },
  "criteria": {
    "has_light_blue_dye": {
      "trigger": "minecraft:inventory_changed",
      "conditions": {
        "items": [
          {
            "items": [
              "minecraft:light_blue_dye"
            ]
          }
        ]
      }
    },
    "has_the_recipe": {
      "trigger": "minecraft:recipe_unlocked",
      "conditions": {
        "recipe": "electromatic:light_blue_copper_wire"
      }
    }
  },
  "requirements": [
    [
      "has_light_blue_dye",
      "has_the_recipe"
    ]
  ]
}